constants.py
stronghold.py
stronghold-1.4.1.dist-info/METADATA
stronghold-1.4.1.dist-info/RECORD
stronghold-1.4.1.dist-info/WHEEL
stronghold-1.4.1.dist-info/entry_points.txt
stronghold-1.4.1.dist-info/top_level.txt
