Metadata-Version: 2.1
Name: stronghold
Version: 1.4.1
Summary: Securely configure your Mac from the terminal.
Home-page: https://github.com/alichtman/stronghold
Author: alichtman
Author-email: aaronlichtman@gmail.com
License: UNKNOWN
Project-URL: Bug Reports, https://github.com/alichtman/stronghold/issues
Project-URL: Donations, https://www.patreon.com/alichtman
Keywords: fortify stronghold system configuration security firewall hardening secure
Platform: UNKNOWN
Classifier: Development Status :: 5 - Production/Stable
Classifier: Intended Audience :: Developers
Classifier: Intended Audience :: End Users/Desktop
Classifier: Intended Audience :: System Administrators
Classifier: Topic :: Security
Classifier: Topic :: System :: Installation/Setup
Classifier: Topic :: System :: Logging
Classifier: Topic :: System :: Monitoring
Classifier: Topic :: System :: Networking
Classifier: Topic :: System :: Networking :: Firewalls
Classifier: Topic :: System :: Operating System
Classifier: Topic :: Utilities
Classifier: Operating System :: MacOS
Classifier: Natural Language :: English
Classifier: License :: OSI Approved :: MIT License
Classifier: Programming Language :: Python :: 3
Classifier: Programming Language :: Python :: 3.4
Classifier: Programming Language :: Python :: 3.5
Classifier: Programming Language :: Python :: 3.6
Requires-Python: >=3
Requires-Dist: colorama (>=0.3.9)
Requires-Dist: inquirer (>=2.2.0)
Requires-Dist: Click
